jaxonfunctions/__init__.py
jaxonfunctions/rl/__init__.py
jaxonfunctions/rl/value_learning.py
jaxonfunctions-0.1.0.dist-info/METADATA
jaxonfunctions-0.1.0.dist-info/WHEEL
jaxonfunctions-0.1.0.dist-info/licenses/LICENSE
jaxonfunctions-0.1.0.dist-info/RECORD
