Metadata-Version: 2.3
Name: jaxonfunctions
Version: 0.1.0
Summary: Functions for JAX
Author-email: "Artur A. Galstyan" <mail@arturgalstyan.dev>
License: MIT License
License-File: LICENSE
Requires-Python: >=3.10
Requires-Dist: beartype
Requires-Dist: jax
Requires-Dist: jaxlib
Requires-Dist: jaxtyping
Requires-Dist: numpy
Requires-Dist: typing-extensions
Provides-Extra: dev
Requires-Dist: mkdocs; extra == 'dev'
Requires-Dist: pre-commit; extra == 'dev'
Requires-Dist: pytest; extra == 'dev'
